text_embeddings_inference_client/__init__.py
text_embeddings_inference_client/api/__init__.py
text_embeddings_inference_client/api/text_embeddings_inference/__init__.py
text_embeddings_inference_client/api/text_embeddings_inference/embed.py
text_embeddings_inference_client/api/text_embeddings_inference/get_model_info.py
text_embeddings_inference_client/api/text_embeddings_inference/health.py
text_embeddings_inference_client/api/text_embeddings_inference/metrics.py
text_embeddings_inference_client/api/text_embeddings_inference/openai_embed.py
text_embeddings_inference_client/client.py
text_embeddings_inference_client/errors.py
text_embeddings_inference_client/models/__init__.py
text_embeddings_inference_client/models/embed_request.py
text_embeddings_inference_client/models/error_response.py
text_embeddings_inference_client/models/error_type.py
text_embeddings_inference_client/models/open_ai_compat_embedding.py
text_embeddings_inference_client/models/open_ai_compat_error_response.py
text_embeddings_inference_client/models/open_ai_compat_request.py
text_embeddings_inference_client/models/open_ai_compat_response.py
text_embeddings_inference_client/models/open_ai_compat_usage.py
text_embeddings_inference_client/py.typed
text_embeddings_inference_client/types.py
text_embeddings_inference_client-0.1.0.dist-info/METADATA
text_embeddings_inference_client-0.1.0.dist-info/WHEEL
text_embeddings_inference_client-0.1.0.dist-info/RECORD
